README.md
setup.py
ImageMetaTag/__init__.py
ImageMetaTag/db.py
ImageMetaTag/img_dict.py
ImageMetaTag/savefig.py
ImageMetaTag/webpage.py
ImageMetaTag.egg-info/PKG-INFO
ImageMetaTag.egg-info/SOURCES.txt
ImageMetaTag.egg-info/dependency_links.txt
ImageMetaTag.egg-info/top_level.txt
ImageMetaTag/javascript/imt_dropdown.js
ImageMetaTag/javascript/pako_inflate.js