Metadata-Version: 1.1
Name: ImageMetaTag
Version: 0.6.9
Summary: Image metadata tagging, database and presentation
Home-page: https://github.com/SciTools-incubator/image-meta-tag
Author: Malcolm Brooks
Author-email: UNKNOWN
License: BSD3
Platform: UNKNOWN
Classifier: Programming Language :: Python :: 2.7
